{
    "disableTopPadding": false,
    "isSettingDescription": false,
    "showAsSectionHeader": false,
    "id": "ComplianceWindows10_DeviceHealth_complianceWindowsDeviceHealthAttestationHeader_10882",
    "dataType": 8,
    "category": 39,
    "nameResourceKey": "complianceWindowsDeviceHealthAttestationHeader",
    "inputControlLength": 0,
    "validation": [],
    "childSettings": [],
    "options": [],
    "isRequired": false,
    "booleanActions": 0,
    "policyType": 35,
    "flipChildrenEnabledLogic": false,
    "readOnly": false,
    "writeOnce": false,
    "enabled": true,
    "multiItemIncludeSelectAll": false
}