{
    "id": "deviceConfiguration--windows10TeamGeneralConfiguration_deviceAccountExchangeServerAddress",
    "valueType": "string",
    "displayName": "Device account exchange server address",
    "isTopLevel": true,
    "description": "Device account exchange server address",
    "placeholderText": null,
    "documentationUrl": null,
    "headerTitle": null,
    "headerSubtitle": null,
    "keywords": [
        ""
    ],
    "constraints": [
        {
            "@odata.type": "#microsoft.graph.deviceManagementSettingStringLengthConstraint",
            "minimumLength": null,
            "maximumLength": 1000
        }
    ],
    "dependencies": []
}