{
    "hideAddById": false,
    "hideAddByUrl": false,
    "includeWebApps": false,
    "excludeAppIds": [],
    "appTypes": [],
    "addNewItemsToTop": false,
    "blockInlineAdd": false,
    "hideHeader": false,
    "hideCsvImport": false,
    "hideCsvExport": false,
    "hideTableSection": false,
    "isDependentTable": false,
    "labelAndButtonsInline": false,
    "hideLabelAndButtons": false,
    "combineUniquenessKeysIntoSingleKey": false,
    "columns": [
        {
            "hideFromEditor": false,
            "hideFromGrid": false,
            "isEditableInline": false,
            "metadata": {
                "id": "Windows10General_Display_exclusionAppListColumn_6596",
                "dataType": 20,
                "category": 48,
                "nameResourceKey": "exclusionAppListColumn",
                "emptyValueResourceKey": "appColumnExamples",
                "inputControlLength": 0,
                "validation": [],
                "childSettings": [],
                "options": [],
                "isRequired": false,
                "entityKey": "gdiAppListColumn",
                "booleanActions": 0,
                "policyType": 79,
                "flipChildrenEnabledLogic": false,
                "readOnly": false,
                "writeOnce": false,
                "enabled": true,
                "multiItemIncludeSelectAll": false
            }
        }
    ],
    "reorderableRows": false,
    "promptOnDelete": false,
    "showNumOfRowsAddedText": false,
    "showKioskCustomBrowseSection": false,
    "entityKeyMap": {},
    "id": "Windows10General_Display_DisplayAppListWithGdiDPIScalingTurnedOffName",
    "dataType": 21,
    "category": 48,
    "nameResourceKey": "DisplayAppListWithGdiDPIScalingTurnedOffName",
    "descriptionResourceKey": "DisplayAppListWithGdiDPIScalingTurnedOffDescription",
    "inputControlLength": 0,
    "validation": [],
    "childSettings": [],
    "options": [],
    "isRequired": false,
    "entityKey": "displayAppListWithGdiDPIScalingTurnedOff",
    "booleanActions": 0,
    "policyType": 79,
    "flipChildrenEnabledLogic": false,
    "readOnly": false,
    "writeOnce": false,
    "enabled": true,
    "multiItemIncludeSelectAll": false
}